orgco/convert.py
orgco/__init__.py
orgco/orgalyzer.py
orgco/orgco.py
orgco-0.2.0.dist-info/entry_points.txt
orgco-0.2.0.dist-info/metadata.json
orgco-0.2.0.dist-info/top_level.txt
orgco-0.2.0.dist-info/METADATA
orgco-0.2.0.dist-info/RECORD
orgco-0.2.0.dist-info/WHEEL
orgco-0.2.0.dist-info/DESCRIPTION.rst
