Metadata-Version: 2.0
Name: orgco
Version: 0.2.0
Summary: With orgco you can convert Emacs' orgmode to other formats.
Home-page: https://github.com/paetzke/orgco
Author: Friedrich Paetzke
Author-email: paetzke@fastmail.fm
License: BSD
Platform: UNKNOWN
Classifier: Intended Audience :: Developers
Classifier: License :: OSI Approved :: BSD License
Classifier: Operating System :: OS Independent
Classifier: Programming Language :: Python
Classifier: Programming Language :: Python :: 2
Classifier: Programming Language :: Python :: 2.7
Classifier: Programming Language :: Python :: 3
Classifier: Programming Language :: Python :: 3.3
Classifier: Programming Language :: Python :: Implementation :: CPython
Classifier: Programming Language :: Python :: Implementation :: PyPy
Classifier: Topic :: Software Development :: Libraries :: Python Modules
Classifier: Topic :: Text Editors :: Emacs
Classifier: Topic :: Text Processing
Requires-Dist: pygments
